temperature_ctrl.v
`timescale 1ns / 1ps
module temperature_ctrl(
    input  wire clk,
    input  wire rst_n,
    input  wire [7:0] temperature,
    output reg heater_on,
    output reg cooler_on,
    output reg buzzer
);

    // Realistic temperature range for stored grains: 20-30°C (Source: USDA)
    parameter TEMP_LOW  = 8'd20;
    parameter TEMP_HIGH = 8'd30;

    always @(posedge clk or negedge rst_n) begin
        if(!rst_n) begin
            heater_on <= 1'b0;
            cooler_on <= 1'b0;
            buzzer    <= 1'b0;
        end
        else begin
            if(temperature < TEMP_LOW) begin
                heater_on <= 1'b1;
                cooler_on <= 1'b0;
                buzzer    <= 1'b1;
            end
            else if(temperature > TEMP_HIGH) begin
                heater_on <= 1'b0;
                cooler_on <= 1'b1;
                buzzer    <= 1'b1;
            end
            else begin
                heater_on <= 1'b0;
                cooler_on <= 1'b0;
                buzzer    <= 1'b0;
            end
        end
    end
endmodule

humidity_ctrl.v
`timescale 1ns / 1ps

module humidity_ctrl(
    input  wire clk,
    input  wire rst_n,
    input  wire [7:0] humidity,   // Humidity input in %
    output reg fan_on,
    output reg alert,
    output reg buzzer
);

    
    // Source: FAO Guidelines - Ideal 12-14% moisture (~60-65% RH at 25°C)
    parameter HUMIDITY_HIGH = 8'd65;
    parameter HUMIDITY_LOW  = 8'd40;

    always @(posedge clk or negedge rst_n) begin
        if(!rst_n) begin
            fan_on  <= 1'b0;
            alert   <= 1'b0;
            buzzer  <= 1'b0;
        end
        else begin
            if(humidity > HUMIDITY_HIGH) begin
                fan_on  <= 1'b1;
                alert   <= 1'b1;
                buzzer  <= 1'b1;   // Too humid
            end
            else if(humidity < HUMIDITY_LOW) begin
                fan_on  <= 1'b0;
                alert   <= 1'b1;
                buzzer  <= 1'b1;   // Too dry
            end
            else begin
                fan_on  <= 1'b0;
                alert   <= 1'b0;
                buzzer  <= 1'b0;   // Normal
            end
        end
    end
endmodule

i2c_master_skel.v
`timescale 1ns / 1ps

module i2c_master_skel (
    input  wire clk,      // System clock
    input  wire rst_n,    // Active-low reset
    output reg  scl,      // I2C clock line
    output reg  sda,      // I2C data line
    output reg  start,    // START pulse
    output reg  stop      // STOP pulse
);

    reg [7:0] state;
    parameter IDLE=0, START_COND=1, DATA_TRANSFER=2, STOP_COND=3;

    always @(posedge clk or negedge rst_n) begin
        if(!rst_n) begin
            scl   <= 1'b1;
            sda   <= 1'b1;
            start <= 1'b0;
            stop  <= 1'b0;
            state <= IDLE;
        end
        else begin
            case(state)
                IDLE: begin
                    start <= 1'b1;     // Generate START
                    sda   <= 1'b0;
                    state <= START_COND;
                end
                START_COND: begin
                    start <= 1'b0;
                    scl   <= ~scl;     // Toggle clock
                    if(scl) state <= DATA_TRANSFER;
                end
                DATA_TRANSFER: begin
                    sda <= ~sda;       // Toggle data line
                    scl <= ~scl;
                    if(scl && sda) state <= STOP_COND;
                end
                STOP_COND: begin
                    stop  <= 1'b1;     // Generate STOP
                    sda   <= 1'b1;
                    scl   <= 1'b1;
                    state <= IDLE;
                end
            endcase
        end
    end
endmodule

tb_i2c_env.v
`timescale 1ns / 1ps
module tb_i2c_env;

    reg clk, rst_n;
    reg [7:0] humidity, temperature;
    wire fan_on, alert, buzzer_h;
    wire heater_on, cooler_on, buzzer_t;
    wire scl, sda, start, stop;

    // I2C Master
    i2c_master_skel i2c_master (
        .clk(clk),
        .rst_n(rst_n),
        .scl(scl),
        .sda(sda),
        .start(start),
        .stop(stop)
    );

    // Humidity Control
    humidity_ctrl hum_ctrl (
        .clk(clk),
        .rst_n(rst_n),
        .humidity(humidity),
        .fan_on(fan_on),
        .alert(alert),
        .buzzer(buzzer_h)
    );

    // Temperature Control
    temperature_ctrl temp_ctrl (
        .clk(clk),
        .rst_n(rst_n),
        .temperature(temperature),
        .heater_on(heater_on),
        .cooler_on(cooler_on),
        .buzzer(buzzer_t)
    );

    // Combine buzzer signals (either humidity or temp issue)
    wire buzzer = buzzer_h | buzzer_t;

    // Clock generation
    initial clk = 0;
    always #5 clk = ~clk;

    initial begin
        $dumpfile("grain_system.vcd");
        $dumpvars(0, tb_i2c_env);

        rst_n = 0;
        humidity = 8'd55;
        temperature = 8'd25;
        #20 rst_n = 1;

        // 1. Normal
        #100;
        humidity = 8'd68; temperature = 8'd27;

        // 2. High humidity
        #100;
        humidity = 8'd75; temperature = 8'd22;

        // 3. Low temperature
        #100;
        humidity = 8'd60; temperature = 8'd17;

        // 4. High temperature
        #100;
        humidity = 8'd64; temperature = 8'd35;

        // 5. Normal again
        #100;
        humidity = 8'd55; temperature = 8'd25;

        #100 $finish;
    end

    initial begin
        $monitor("Time=%0t | Temp=%0d°C | Hum=%0d%% | Fan=%b | Alert=%b | Heater=%b | Cooler=%b | Buzzer=%b",
                 $time, temperature, humidity, fan_on, alert, heater_on, cooler_on, buzzer);
    end

endmodule

grain_system.vcd
$date
   Sat Nov 22 15:06:02 2025
$end
$version
  2019.2
$end
$timescale
  1ps
$end
$scope module tb_i2c_env $end
$var reg 1 ! clk $end
$var reg 1 " rst_n $end
$var reg 8 # humidity [7:0] $end
$var reg 8 $ temperature [7:0] $end
$var wire 1 % fan_on $end
$var wire 1 & alert $end
$var wire 1 ' buzzer_h $end
$var wire 1 ( heater_on $end
$var wire 1 ) cooler_on $end
$var wire 1 * buzzer_t $end
$var wire 1 + scl $end
$var wire 1 , sda $end
$var wire 1 - start $end
$var wire 1 . stop $end
$var wire 1 / buzzer $end
$scope module i2c_master $end
$var wire 1 0 clk $end
$var wire 1 1 rst_n $end
$var reg 1 2 scl $end
$var reg 1 3 sda $end
$var reg 1 4 start $end
$var reg 1 5 stop $end
$var reg 8 6 state [7:0] $end
$var parameter 32 7 IDLE [31:0] $end
$var parameter 32 8 START_COND [31:0] $end
$var parameter 32 9 DATA_TRANSFER [31:0] $end
$var parameter 32 : STOP_COND [31:0] $end
$upscope $end
$scope module hum_ctrl $end
$var wire 1 ; clk $end
$var wire 1 < rst_n $end
$var wire 8 = humidity [7:0] $end
$var reg 1 > fan_on $end
$var reg 1 ? alert $end
$var reg 1 @ buzzer $end
$var parameter 8 A HUMIDITY_HIGH [7:0] $end
$var parameter 8 B HUMIDITY_LOW [7:0] $end
$upscope $end
$scope module temp_ctrl $end
$var wire 1 C clk $end
$var wire 1 D rst_n $end
$var wire 8 E temperature [7:0] $end
$var reg 1 F heater_on $end
$var reg 1 G cooler_on $end
$var reg 1 H buzzer $end
$var parameter 8 I TEMP_LOW [7:0] $end
$var parameter 8 J TEMP_HIGH [7:0] $end
$upscope $end
$upscope $end
$enddefinitions $end
#0
$dumpvars
0!
0"
b110111 #
b11001 $
0%
0&
0'
0(
0)
0*
1+
1,
0-
0.
0/
00
01
12
13
04
05
b0 6
b0 7
b1 8
b10 9
b11 :
0;
0<
b110111 =
0>
0?
0@
b1000001 A
b101000 B
0C
0D
b11001 E
0F
0G
0H
b10100 I
b11110 J
$end
#5000
1!
10
1;
1C
#10000
0!
00
0;
0C
#15000
1!
10
1;
1C
#20000
0!
1"
00
11
0;
1<
0C
1D
#25000
1!
0,
1-
10
03
14
b1 6
1;
1C
#30000
0!
00
0;
0C
#35000
1!
0+
0-
10
02
04
b10 6
1;
1C
#40000
0!
00
0;
0C
#45000
1!
1+
1,
10
12
13
1;
1C
#50000
0!
00
0;
0C
#55000
1!
0+
0,
10
02
03
b11 6
1;
1C
#60000
0!
00
0;
0C
#65000
1!
1+
1,
1.
10
12
13
15
b0 6
1;
1C
#70000
0!
00
0;
0C
#75000
1!
0,
1-
10
03
14
b1 6
1;
1C
#80000
0!
00
0;
0C
#85000
1!
0+
0-
10
02
04
b10 6
1;
1C
#90000
0!
00
0;
0C
#95000
1!
1+
1,
10
12
13
1;
1C
#100000
0!
00
0;
0C
#105000
1!
0+
0,
10
02
03
b11 6
1;
1C
#110000
0!
00
0;
0C
#115000
1!
1+
1,
10
12
13
b0 6
1;
1C
#120000
0!
b1000100 #
b11011 $
00
0;
b1000100 =
0C
b11011 E
#125000
1!
1%
1&
1'
0,
1-
1/
10
03
14
b1 6
1;
1>
1?
1@
1C
#130000
0!
00
0;
0C
#135000
1!
0+
0-
10
02
04
b10 6
1;
1C
#140000
0!
00
0;
0C
#145000
1!
1+
1,
10
12
13
1;
1C
#150000
0!
00
0;
0C
#155000
1!
0+
0,
10
02
03
b11 6
1;
1C
#160000
0!
00
0;
0C
#165000
1!
1+
1,
10
12
13
b0 6
1;
1C
#170000
0!
00
0;
0C
#175000
1!
0,
1-
10
03
14
b1 6
1;
1C
#180000
0!
00
0;
0C
#185000
1!
0+
0-
10
02
04
b10 6
1;
1C
#190000
0!
00
0;
0C
#195000
1!
1+
1,
10
12
13
1;
1C
#200000
0!
00
0;
0C
#205000
1!
0+
0,
10
02
03
b11 6
1;
1C
#210000
0!
00
0;
0C
#215000
1!
1+
1,
10
12
13
b0 6
1;
1C
#220000
0!
b1001011 #
b10110 $
00
0;
b1001011 =
0C
b10110 E
#225000
1!
0,
1-
10
03
14
b1 6
1;
1C
#230000
0!
00
0;
0C
#235000
1!
0+
0-
10
02
04
b10 6
1;
1C
#240000
0!
00
0;
0C
#245000
1!
1+
1,
10
12
13
1;
1C
#250000
0!
00
0;
0C
#255000
1!
0+
0,
10
02
03
b11 6
1;
1C
#260000
0!
00
0;
0C
#265000
1!
1+
1,
10
12
13
b0 6
1;
1C
#270000
0!
00
0;
0C
#275000
1!
0,
1-
10
03
14
b1 6
1;
1C
#280000
0!
00
0;
0C
#285000
1!
0+
0-
10
02
04
b10 6
1;
1C
#290000
0!
00
0;
0C
#295000
1!
1+
1,
10
12
13
1;
1C
#300000
0!
00
0;
0C
#305000
1!
0+
0,
10
02
03
b11 6
1;
1C
#310000
0!
00
0;
0C
#315000
1!
1+
1,
10
12
13
b0 6
1;
1C
#320000
0!
b111100 #
b10001 $
00
0;
b111100 =
0C
b10001 E
#325000
1!
0%
0&
0'
1(
1*
0,
1-
1/
10
03
14
b1 6
1;
0>
0?
0@
1C
1F
1H
#330000
0!
00
0;
0C
#335000
1!
0+
0-
10
02
04
b10 6
1;
1C
#340000
0!
00
0;
0C
#345000
1!
1+
1,
10
12
13
1;
1C
#350000
0!
00
0;
0C
#355000
1!
0+
0,
10
02
03
b11 6
1;
1C
#360000
0!
00
0;
0C
#365000
1!
1+
1,
10
12
13
b0 6
1;
1C
#370000
0!
00
0;
0C
#375000
1!
0,
1-
10
03
14
b1 6
1;
1C
#380000
0!
00
0;
0C
#385000
1!
0+
0-
10
02
04
b10 6
1;
1C
#390000
0!
00
0;
0C
#395000
1!
1+
1,
10
12
13
1;
1C
#400000
0!
00
0;
0C
#405000
1!
0+
0,
10
02
03
b11 6
1;
1C
#410000
0!
00
0;
0C
#415000
1!
1+
1,
10
12
13
b0 6
1;
1C
#420000
0!
b1000000 #
b100011 $
00
0;
b1000000 =
0C
b100011 E
#425000
1!
0(
1)
0,
1-
10
03
14
b1 6
1;
1C
0F
1G
#430000
0!
00
0;
0C
#435000
1!
0+
0-
10
02
04
b10 6
1;
1C
#440000
0!
00
0;
0C
#445000
1!
1+
1,
10
12
13
1;
1C
#450000
0!
00
0;
0C
#455000
1!
0+
0,
10
02
03
b11 6
1;
1C
#460000
0!
00
0;
0C
#465000
1!
1+
1,
10
12
13
b0 6
1;
1C
#470000
0!
00
0;
0C
#475000
1!
0,
1-
10
03
14
b1 6
1;
1C
#480000
0!
00
0;
0C
#485000
1!
0+
0-
10
02
04
b10 6
1;
1C
#490000
0!
00
0;
0C
#495000
1!
1+
1,
10
12
13
1;
1C
#500000
0!
00
0;
0C
#505000
1!
0+
0,
10
02
03
b11 6
1;
1C
#510000
0!
00
0;
0C
#515000
1!
1+
1,
10
12
13
b0 6
1;
1C
#520000
0!
b110111 #
b11001 $
00
0;
b110111 =
0C
b11001 E
#525000
1!
0)
0*
0,
1-
0/
10
03
14
b1 6
1;
1C
0G
0H
#530000
0!
00
0;
0C
#535000
1!
0+
0-
10
02
04
b10 6
1;
1C
#540000
0!
00
0;
0C
#545000
1!
1+
1,
10
12
13
1;
1C
#550000
0!
00
0;
0C
#555000
1!
0+
0,
10
02
03
b11 6
1;
1C
#560000
0!
00
0;
0C
#565000
1!
1+
1,
10
12
13
b0 6
1;
1C
#570000
0!
00
0;
0C
#575000
1!
0,
1-
10
03
14
b1 6
1;
1C
#580000
0!
00
0;
0C
#585000
1!
0+
0-
10
02
04
b10 6
1;
1C
#590000
0!
00
0;
0C
#595000
1!
1+
1,
10
12
13
1;
1C
#600000
0!
00
0;
0C
#605000
1!
0+
0,
10
02
03
b11 6
1;
1C
#610000
0!
00
0;
0C
#615000
1!
1+
1,
10
12
13
b0 6
1;
1C
